asposeslidescloud/__init__.py
asposeslidescloud/api_client.py
asposeslidescloud/configuration.py
asposeslidescloud/error_message.py
asposeslidescloud/oauth_response.py
asposeslidescloud/rest.py
asposeslidescloud/apis/__init__.py
asposeslidescloud/apis/api_base.py
asposeslidescloud/apis/slides_api.py
asposeslidescloud/apis/slides_async_api.py
asposeslidescloud/models/__init__.py
asposeslidescloud/models/accent_element.py
asposeslidescloud/models/access_permissions.py
asposeslidescloud/models/add_layout_slide.py
asposeslidescloud/models/add_master_slide.py
asposeslidescloud/models/add_shape.py
asposeslidescloud/models/add_slide.py
asposeslidescloud/models/alpha_bi_level_effect.py
asposeslidescloud/models/alpha_ceiling_effect.py
asposeslidescloud/models/alpha_floor_effect.py
asposeslidescloud/models/alpha_inverse_effect.py
asposeslidescloud/models/alpha_modulate_effect.py
asposeslidescloud/models/alpha_modulate_fixed_effect.py
asposeslidescloud/models/alpha_replace_effect.py
asposeslidescloud/models/api_info.py
asposeslidescloud/models/arc_to_path_segment.py
asposeslidescloud/models/array_element.py
asposeslidescloud/models/arrow_head_properties.py
asposeslidescloud/models/audio_frame.py
asposeslidescloud/models/axes.py
asposeslidescloud/models/axis.py
asposeslidescloud/models/axis_type.py
asposeslidescloud/models/bar_element.py
asposeslidescloud/models/base64_input_file.py
asposeslidescloud/models/bi_level_effect.py
asposeslidescloud/models/block_element.py
asposeslidescloud/models/blur_effect.py
asposeslidescloud/models/blur_image_effect.py
asposeslidescloud/models/border_box_element.py
asposeslidescloud/models/box_element.py
asposeslidescloud/models/bubble_chart_data_point.py
asposeslidescloud/models/bubble_series.py
asposeslidescloud/models/camera.py
asposeslidescloud/models/caption_track.py
asposeslidescloud/models/caption_tracks.py
asposeslidescloud/models/chart.py
asposeslidescloud/models/chart_category.py
asposeslidescloud/models/chart_lines_format.py
asposeslidescloud-26.1.0.dist-info/LICENSE
asposeslidescloud-26.1.0.dist-info/METADATA
asposeslidescloud-26.1.0.dist-info/WHEEL
asposeslidescloud-26.1.0.dist-info/top_level.txt
asposeslidescloud-26.1.0.dist-info/RECORD
