Metadata-Version: 2.1
Name: asposeslidescloud
Version: 26.1.0
Summary: Aspose.Slides Cloud SDK for Python
Home-page: 
Author: Victor Putrov
Author-email: vistor.putrov@aspose.com
Classifier: Programming Language :: Python :: 3
Classifier: License :: OSI Approved :: MIT License
Classifier: Operating System :: OS Independent
License-File: LICENSE
Requires-Dist: urllib3 >=1.15.1
Requires-Dist: six >=1.10
Requires-Dist: certifi >=14.05.14
